dora/__init__.py
dora/analyzer.py
dora/config_loader.py
dora/data_loader.py
dora/kaggle.py
dora/main.py
dora/plots/__init__.py
dora/plots/bivariate.py
dora/plots/multivariate.py
dora/plots/styling.py
dora/plots/univariate.py
dora/plots/utils.py
dora/profiling.py
dora/reporting/__init__.py
dora/reporting/generator.py
dora/reporting/templates/report_template.html
dora/schema.py
dora_eda-4.0.2.dist-info/METADATA
dora_eda-4.0.2.dist-info/WHEEL
dora_eda-4.0.2.dist-info/entry_points.txt
dora_eda-4.0.2.dist-info/licenses/LICENSE
dora_eda-4.0.2.dist-info/RECORD
