Metadata-Version: 2.4
Name: dora-eda
Version: 4.0.2
Summary: Exploratory data analysis and presentation tool
License: MIT
License-File: LICENSE
Author: Asif Sayyed
Author-email: asifdotexe@gmail.com
Requires-Python: >=3.13
Classifier: Programming Language :: Python :: 3
Classifier: License :: OSI Approved :: MIT License
Classifier: Operating System :: OS Independent
Classifier: Topic :: Scientific/Engineering :: Information Analysis
Requires-Dist: jinja2 (>=3.1.6,<4.0.0)
Requires-Dist: kagglehub (==0.3.13)
Requires-Dist: matplotlib (>=3.10.6,<4.0.0)
Requires-Dist: numpy (>=2.3.3,<3.0.0)
Requires-Dist: openpyxl (>=3.1.5,<4.0.0)
Requires-Dist: pandas (>=2.3.3,<3.0.0)
Requires-Dist: pyarrow (>=21.0.0,<22.0.0)
Requires-Dist: pydantic (>=2.12.5,<3.0.0)
Requires-Dist: pyyaml (>=6.0.3,<7.0.0)
Requires-Dist: seaborn (>=0.13.2,<0.14.0)
Requires-Dist: streamlit (>=1.53.0,<2.0.0)
Requires-Dist: tqdm (>=4.67.1,<5.0.0)
Requires-Dist: typer[rich] (>=0.19.2,<0.20.0)
Project-URL: Repository, https://github.com/Asifdotexe/DORA
